{
  "139448": {
    "toss_winner": "Sri Lanka",
    "decision": "bowl",
    "match_winner": "Pakistan"
  },
  "139437": {
    "toss_winner": "New Zealand",
    "decision": "bat",
    "match_winner": "England"
  },
  "139426": {
    "toss_winner": "Zimbabwe",
    "decision": "bowl",
    "match_winner": "India"
  },
  "139415": {
    "toss_winner": "South Africa",
    "decision": "bowl",
    "match_winner": "South Africa"
  },
  "139404": {
    "toss_winner": "Sri Lanka",
    "decision": "bowl",
    "match_winner": "New Zealand"
  },
  "139393": {
    "toss_winner": "Pakistan",
    "decision": "bat",
    "match_winner": "England"
  },
  "139382": {
    "toss_winner": "Zimbabwe",
    "decision": "bowl",
    "match_winner": "West Indies"
  },
  "139381": {
    "toss_winner": "South Africa",
    "decision": "bat",
    "match_winner": "South Africa"
  },
  "139373": {
    "toss_winner": "Sri Lanka",
    "decision": "bowl",
    "match_winner": "England"
  },
  "147016": {
    "toss_winner": "Bahrain",
    "decision": "bowl",
    "match_winner": "Match tied (Bahrain"
  },
  "147005": {
    "toss_winner": "Bhutan",
    "decision": "bat",
    "match_winner": "Bhutan"
  },
  "146994": {
    "toss_winner": "Thailand",
    "decision": "bowl",
    "match_winner": "Bahrain"
  },
  "146983": {
    "toss_winner": "Japan",
    "decision": "bat",
    "match_winner": "Japan"
  },
  "146961": {
    "toss_winner": "Bhutan",
    "decision": "bowl",
    "match_winner": "Thailand"
  }
}